torchstack/__init__.py
torchstack/configuration.py
torchstack/distribute.py
torchstack/ensemble.py
torchstack/member.py
torchstack/backup/_optimization.py
torchstack/backup/cag copy.py
torchstack/backup/ensemble_generator.py
torchstack/backup/generator.py
torchstack/backup/tokenization/__init__.py
torchstack/backup/tokenization/base.py
torchstack/backup/tokenization/projection.py
torchstack/backup/tokenization/union_vocabulary.py
torchstack/models/__init__.py
torchstack/models/causal_model.py
torchstack/strategies/__init__.py
torchstack/strategies/base.py
torchstack/strategies/cag.py
torchstack/strategies/deepen.py
torchstack/strategies/gac.py
torchstack/strategies/unite.py
torchstack-0.1.17.dist-info/LICENSE
torchstack-0.1.17.dist-info/METADATA
torchstack-0.1.17.dist-info/WHEEL
torchstack-0.1.17.dist-info/top_level.txt
torchstack-0.1.17.dist-info/RECORD
