Metadata-Version: 2.2
Name: torchstack
Version: 0.1.17
Summary: Leverage torchstack to build transfor based ensembles
Project-URL: Homepage, https://github.com/bodeby/torchstack
Project-URL: Issues, https://github.com/bodeby/torchstack/issues
Project-URL: Documentation, https://bodeby.github.io/torchstack/
Requires-Python: >=3.10
License-File: LICENSE
Requires-Dist: numpy<2.0,>=1.23.5
Requires-Dist: pydantic>=2.10.1
Requires-Dist: ruff>=0.7.4
Requires-Dist: torch>=2.4.1
Requires-Dist: transformers>=4.45.2
